django_hx/__init__.py
django_hx/apps.py
django_hx/decorators.py
django_hx/tests.py
django_hx/utils.py
django_hx-0.1.2.dist-info/METADATA
django_hx-0.1.2.dist-info/WHEEL
django_hx-0.1.2.dist-info/RECORD
