Metadata-Version: 2.4
Name: django-hx
Version: 0.1.2
Summary: Tools for using Django with HTMX
Author-email: "Erlend D. Handeland" <hanerlend@icloud.com>
Requires-Python: >=3.11
Requires-Dist: django-template-partials>=25.2
